langchainmsai/__init__.py
langchainmsai/_api/__init__.py
langchainmsai/_api/deprecation.py
langchainmsai/_api/path.py
langchainmsai/adapters/__init__.py
langchainmsai/adapters/openai.py
langchainmsai/agents/__init__.py
langchainmsai/agents/agent.py
langchainmsai/agents/agent_iterator.py
langchainmsai/agents/agent_toolkits/__init__.py
langchainmsai/agents/agent_toolkits/ainetwork/__init__.py
langchainmsai/agents/agent_toolkits/ainetwork/toolkit.py
langchainmsai/agents/agent_toolkits/amadeus/toolkit.py
langchainmsai/agents/agent_toolkits/azure_cognitive_services.py
langchainmsai/agents/agent_toolkits/base.py
langchainmsai/agents/agent_toolkits/clickup/__init__.py
langchainmsai/agents/agent_toolkits/clickup/toolkit.py
langchainmsai/agents/agent_toolkits/conversational_retrieval/__init__.py
langchainmsai/agents/agent_toolkits/conversational_retrieval/openai_functions.py
langchainmsai/agents/agent_toolkits/conversational_retrieval/tool.py
langchainmsai/agents/agent_toolkits/csv/__init__.py
langchainmsai/agents/agent_toolkits/file_management/__init__.py
langchainmsai/agents/agent_toolkits/file_management/toolkit.py
langchainmsai/agents/agent_toolkits/github/__init__.py
langchainmsai/agents/agent_toolkits/github/toolkit.py
langchainmsai/agents/agent_toolkits/gitlab/__init__.py
langchainmsai/agents/agent_toolkits/gitlab/toolkit.py
langchainmsai/agents/agent_toolkits/gmail/__init__.py
langchainmsai/agents/agent_toolkits/gmail/toolkit.py
langchainmsai/agents/agent_toolkits/jira/__init__.py
langchainmsai/agents/agent_toolkits/jira/toolkit.py
langchainmsai/agents/agent_toolkits/json/__init__.py
langchainmsai/agents/agent_toolkits/json/base.py
langchainmsai/agents/agent_toolkits/json/prompt.py
langchainmsai/agents/agent_toolkits/json/toolkit.py
langchainmsai/agents/agent_toolkits/multion/__init__.py
langchainmsai/agents/agent_toolkits/multion/toolkit.py
langchainmsai/agents/agent_toolkits/nasa/__init__.py
langchainmsai/agents/agent_toolkits/nasa/toolkit.py
langchainmsai-0.1.0.222.dist-info/LICENSE
langchainmsai-0.1.0.222.dist-info/METADATA
langchainmsai-0.1.0.222.dist-info/WHEEL
langchainmsai-0.1.0.222.dist-info/entry_points.txt
langchainmsai-0.1.0.222.dist-info/RECORD
